petpal/__init__.py
petpal/cli/__init__.py
petpal/cli/cli_graphical_analysis.py
petpal/cli/cli_graphical_plots.py
petpal/cli/cli_idif.py
petpal/cli/cli_parametric_images.py
petpal/cli/cli_pib_processing.py
petpal/cli/cli_plot_tacs.py
petpal/cli/cli_preproc.py
petpal/cli/cli_pvc.py
petpal/cli/cli_reference_tissue_models.py
petpal/cli/cli_stats.py
petpal/cli/cli_tac_fitting.py
petpal/cli/cli_tac_interpolation.py
petpal/cli/cli_vat_processing.py
petpal/input_function/__init__.py
petpal/input_function/blood_input.py
petpal/input_function/idif_necktangle.py
petpal/input_function/pca_guided_idif.py
petpal/kinetic_modeling/__init__.py
petpal/kinetic_modeling/fit_tac_with_rtms.py
petpal/kinetic_modeling/graphical_analysis.py
petpal/kinetic_modeling/parametric_images.py
petpal/kinetic_modeling/reference_tissue_models.py
petpal/kinetic_modeling/rtm_analysis.py
petpal/kinetic_modeling/tac_fitting.py
petpal/kinetic_modeling/tac_interpolation.py
petpal/kinetic_modeling/tac_uncertainty.py
petpal/kinetic_modeling/tcms_as_convolutions.py
petpal/meta/__init__.py
petpal/meta/label_maps.py
petpal/pipelines/__init__.py
petpal/pipelines/kinetic_modeling_steps.py
petpal/pipelines/pca_guided_idif_steps.py
petpal/pipelines/pipelines.py
petpal/pipelines/preproc_steps.py
petpal/pipelines/steps_base.py
petpal/pipelines/steps_containers.py
petpal/preproc/__init__.py
petpal/preproc/decay_correction.py
petpal/preproc/image_operations_4d.py
petpal/preproc/motion_corr.py
petpal/preproc/motion_target.py
petpal/preproc/partial_volume_corrections.py
petpal/preproc/regional_tac_extraction.py
petpal/preproc/register.py
petpal/preproc/segmentation_tools.py
petpal/preproc/standard_uptake_value.py
petpal/preproc/symmetric_geometric_transfer_matrix.py
petpal/utils/__init__.py
petpal/utils/bids_utils.py
petpal/utils/constants.py
petpal/utils/data_driven_image_analyses.py
petpal/utils/decorators.py
petpal/utils/image_io.py
petpal/utils/math_lib.py
petpal/utils/metadata.py
petpal/utils/scan_timing.py
petpal-0.6.0.dist-info/METADATA
petpal-0.6.0.dist-info/WHEEL
petpal-0.6.0.dist-info/entry_points.txt
petpal-0.6.0.dist-info/licenses/LICENSE
petpal-0.6.0.dist-info/RECORD
