Metadata-Version: 2.4
Name: petpal
Version: 0.6.0
Summary: PET-PAL (Positron Emission Tomography Processing and Analysis Library)
Project-URL: Repository, https://github.com/PETPAL-WUSM/PETPAL.git
Author-email: Noah Goldman <noahg@wustl.edu>, Bradley Judge <bjudge@wustl.edu>, Furqan Dar <dar@wustl.edu>, Kenan Oestreich <kenan.oestreich@wustl.edu>
License-File: LICENSE
Classifier: Development Status :: 2 - Pre-Alpha
Classifier: Intended Audience :: Science/Research
Classifier: License :: OSI Approved :: GNU General Public License v3 or later (GPLv3+)
Classifier: Natural Language :: English
Classifier: Programming Language :: Python :: 3
Classifier: Topic :: Scientific/Engineering :: Image Processing
Requires-Python: >=3.12
Requires-Dist: antspyx>=0.5
Requires-Dist: bids-validator
Requires-Dist: docker
Requires-Dist: fslpy
Requires-Dist: lmfit
Requires-Dist: matplotlib
Requires-Dist: networkx
Requires-Dist: nibabel
Requires-Dist: numba
Requires-Dist: numpy
Requires-Dist: pandas
Requires-Dist: pydata-sphinx-theme
Requires-Dist: scikit-learn
Requires-Dist: scipy
Requires-Dist: seaborn
Requires-Dist: simpleitk
Requires-Dist: sphinx
Requires-Dist: sphinx-autoapi
Requires-Dist: sphinx-design
